[
    {
        "key": "dbln",
        "value": "%7B%2261566188837175%22%3A%22k7XUHqTC%22%2C%2261555138716565%22%3A%22rqI4M8so%22%7D",
        "domain": "facebook.com",
        "path": "/login/device-based/",
        "hostOnly": false,
        "creation": "2024-10-17T08:14:30.746Z",
        "lastAccessed": "2024-10-17T08:14:30.747Z"
    },
    {
        "key": "datr",
        "value": "H9oAZ8ND92TGnNmsKSRkAKEd",
        "domain": "facebook.com",
        "path": "/",
        "hostOnly": false,
        "creation": "2024-10-17T08:14:30.747Z",
        "lastAccessed": "2024-10-17T08:14:30.747Z"
    },
    {
        "key": "sb",
        "value": "H9oAZ3p5pfUIt_MOD2hPB-dV",
        "domain": "facebook.com",
        "path": "/",
        "hostOnly": false,
        "creation": "2024-10-17T08:14:30.747Z",
        "lastAccessed": "2024-10-17T08:14:30.747Z"
    },
    {
        "key": "vpd",
        "value": "v1%3B746x393x2.75",
        "domain": "facebook.com",
        "path": "/",
        "hostOnly": false,
        "creation": "2024-10-17T08:14:30.747Z",
        "lastAccessed": "2024-10-17T08:14:30.747Z"
    },
    {
        "key": "ps_l",
        "value": "1",
        "domain": "facebook.com",
        "path": "/",
        "hostOnly": false,
        "creation": "2024-10-17T08:14:30.747Z",
        "lastAccessed": "2024-10-17T08:14:30.747Z"
    },
    {
        "key": "ps_n",
        "value": "1",
        "domain": "facebook.com",
        "path": "/",
        "hostOnly": false,
        "creation": "2024-10-17T08:14:30.747Z",
        "lastAccessed": "2024-10-17T08:14:30.747Z"
    },
    {
        "key": "locale",
        "value": "en_GB",
        "domain": "facebook.com",
        "path": "/",
        "hostOnly": false,
        "creation": "2024-10-17T08:14:30.747Z",
        "lastAccessed": "2024-10-17T08:14:30.747Z"
    },
    {
        "key": "m_pixel_ratio",
        "value": "2.75",
        "domain": "facebook.com",
        "path": "/",
        "hostOnly": false,
        "creation": "2024-10-17T08:14:30.747Z",
        "lastAccessed": "2024-10-17T08:14:30.747Z"
    },
    {
        "key": "c_user",
        "value": "61555138716565",
        "domain": "facebook.com",
        "path": "/",
        "hostOnly": false,
        "creation": "2024-10-17T08:14:30.747Z",
        "lastAccessed": "2024-10-17T08:14:30.747Z"
    },
    {
        "key": "fr",
        "value": "0owwJFuwlJ1Kqhbao.AWXGwAP15hkqDAFXHckbLDYKZI8.BnANof..AAA.0.0.BnEMcv.AWUfzUf8yWk",
        "domain": "facebook.com",
        "path": "/",
        "hostOnly": false,
        "creation": "2024-10-17T08:14:30.747Z",
        "lastAccessed": "2024-10-17T08:14:30.747Z"
    },
    {
        "key": "xs",
        "value": "22%3AzSdWGgwF33vtog%3A2%3A1729152816%3A-1%3A14853",
        "domain": "facebook.com",
        "path": "/",
        "hostOnly": false,
        "creation": "2024-10-17T08:14:30.747Z",
        "lastAccessed": "2024-10-17T08:14:30.747Z"
    },
    {
        "key": "wd",
        "value": "393x746",
        "domain": "facebook.com",
        "path": "/",
        "hostOnly": false,
        "creation": "2024-10-17T08:14:30.747Z",
        "lastAccessed": "2024-10-17T08:14:30.747Z"
    },
    {
        "key": "fbl_st",
        "value": "101221572%3BT%3A28819213",
        "domain": "facebook.com",
        "path": "/",
        "hostOnly": false,
        "creation": "2024-10-17T08:14:30.747Z",
        "lastAccessed": "2024-10-17T08:14:30.747Z"
    },
    {
        "key": "wl_cbv",
        "value": "v2%3Bclient_version%3A2650%3Btimestamp%3A1729152825",
        "domain": "facebook.com",
        "path": "/",
        "hostOnly": false,
        "creation": "2024-10-17T08:14:30.747Z",
        "lastAccessed": "2024-10-17T08:14:30.747Z"
    }
]